__init__.py
mmgp/__init__.py
mmgp/fp8_quanto_bridge.py
mmgp/fp8_quanto_bridge_old.py
mmgp/offload.py
mmgp/quant_router.py
mmgp/quanto_int8_cuda.py
mmgp/quanto_int8_inject.py
mmgp/safetensors2.py
mmgp-3.7.2.dist-info/licenses/LICENSE.md
mmgp-3.7.2.dist-info/METADATA
mmgp-3.7.2.dist-info/WHEEL
mmgp-3.7.2.dist-info/top_level.txt
mmgp-3.7.2.dist-info/RECORD
