Metadata-Version: 2.4
Name: mmgp
Version: 3.7.2
Summary: Memory Management for the GPU Poor
Author-email: deepbeepmeep <deepbeepmeep@yahoo.com>
Requires-Python: >=3.10
License-File: LICENSE.md
Requires-Dist: torch>=2.1.0
Requires-Dist: optimum-quanto
Requires-Dist: accelerate
Requires-Dist: safetensors
Requires-Dist: psutil
Dynamic: license-file
